Workbook

Sheet Instructions
A1: Gartner-Based AI Maturity Assessment for Banking
A3: Welcome to the Banking AI Maturity Assessment Tool. This tool is designed to help you benchmark your institution's AI capabilities against the Gartner AI Maturity Model, specifically adapted for the Financial Services sector. STEPS: 1. Go to the 'Assessment & Targets' tab. 2. For each capability, select your Current Maturity Level (1-5) from the dropdown. - 1: Planning (Ad-hoc, Shadow IT) - 2: Experimenting (PoCs, Innovation Lab) - 3: Stabilization (Standardized Tools, Production governance) - 4: Scaling (Automated MLOps, Integrated into Core Products) - 5: Leading (AI-First Strategy, Industry shaper) 3. Select your Target Maturity Level (Where you need to be in 12-18 months). 4. The 'Gap' will calculate automatically. 5. Assign a Priority (High/Medium/Low) based on business urgency. 6. View the 'Gap Visualization Data' tab for a summary. Reference: Gartner AI Maturity Model (G00821273)

Sheet Definitions
C2: Aligning Ambition with Risk Appetite | D2: Many banks fail because their ambition exceeds their readiness. A mature strategy involves "monitoring and interpreting AI trends" not to chase hype, but to analyze the impact on specific banking functions (e.g., how Large Language Models impact wealth management advisory). A Level 5 bank does not just have a "tech roadmap"; it has a roadmap that spans "all sociotechnical aspects". This means the strategy accounts for the displacement of teller roles, the reskilling of loan officers, and the integration of AI into the bank's ESG (Environmental, Social, and Governance) goals.
C6: The Portfolio Approach | D6: Immature banks treat AI projects like lottery tickets. Mature banks utilize "systematic identification, prioritization, and management" of use cases. In banking, value cannot be decoupled from risk. Low Maturity: Pursuing high-risk/low-value projects (e.g., a customer-facing chatbot that hallucinates). High Maturity: Using a portfolio approach to balance "quick wins" (e.g., internal document search for compliance officers) with "moonshots" (e.g., fully autonomous wealth management). Mature banks rigorously "measure AI use-case portfolio performance", tracking not just technical accuracy (F1 score) but actual P&L impact (e.g., reduction in loan default rates).
C10: The Ecosystem | D10: No bank can build everything alone. Maturity involves "developing external partnerships and alliances" (e.g., partnering with fintechs or cloud providers) while maintaining control over intellectual property. This involves "evolving internal operating models". For a bank, this often looks like a "Hub and Spoke" model: Hub: Central AI team handling standards, platform, and governance. Spoke: Embedded data scientists sitting within the Credit Cards, Mortgage, and Commercial Banking units.
C14: The Soft Skills of Hard Tech | D14: A "lone voice" approach fails. Banks must "deliver skills, training, and literacy" across three tiers: General Staff: Understanding basics and ethics (e.g., "Don't put customer data into public ChatGPT"). Business Leaders: Understanding how to identify value and manage AI P&L. Practitioners: Deep technical upskilling. AI will displace tasks. Mature banks "predict AI-driven workforce implications" early, launching reskilling programs before roles become redundant.
C18: The License to Operate | D18: For banks, this is the most critical pillar. "Best efforts" governance is insufficient when facing regulators like the SEC, OCC, or GDPR/CCPA enforcers. From Policing to Orchestration: Immature governance is a bottleneck. Mature governance involves "identifying and managing governance decision rights" clearly so that teams know exactly who approves a model for production. The "Black Box" Problem: Banks must develop specific policies for "AI security and safety frameworks". This includes Explainable AI (XAI)—ensuring that if an AI denies a loan, the bank can explain why to the customer and the regulator, adhering to Fair Lending laws. Continuous Oversight: Governance isn't a one-time stamp. It requires "continuous AI governance, oversight, and assurance" to detect model drift (e.g., a credit model no longer working due to economic shifts).
C22: Industrializing Intelligence | D22: Managing Technical Debt: A common trap is building AI models on shaky infrastructure. Banks must "manage AI technical debt" aggressively. If a model relies on a fragile script running on a legacy server, it is a systemic risk. MLOps (Machine Learning Operations): Mature banks move from "Ad hoc AI engineering" to "Fusion/collaborative AI engineering". This means implementing CI/CD (Continuous Integration/Continuous Deployment) pipelines specifically for machine learning, allowing for rapid retraining and redeployment of models as market conditions change. Buy vs. Build: A key engineering capability is developing "build vs. buy rationales". Should the bank build its own LLM, or fine-tune an open-source model? The mature bank has a framework for this decision.
C26: Breaking the Silos | D26: Data is the collateral of the AI banking world. The Legacy Challenge: Banks struggle with data locked in mainframes and segregated by product (mortgage data separate from credit card data). Data Lineage: To trust an AI model, the bank must "provide AI data lineage and traceability". You must be able to trace a decision back to the raw data source to satisfy audit requirements. Synthetic Data: Mature banks are increasingly using "synthetic data creation" to train models on rare events (like sophisticated fraud patterns) without exposing real customer PII (Personally Identifiable Information).

Sheet Result Summary
B1: Tier 1 | C1: Maturity level 1 | D1: Maturity level 2 | E1: Maturity level 3 | F1: Maturity level 4 | G1: Maturity level 5
B2: All tier summary | C2: AI is "highly fragmented" or non-existent. | D2: The bank moves to "partially coordinated" efforts. | E2: The organization reaches "strategically aligned" maturity. | F2: AI is "systematically managed" across the enterprise. | G2: The organization is "dynamically adaptive".
B3: All tiers | C3: The Fragmented Bank (Planning) | D3: The Experimental Bank (Emerging) | E3: The Stabilized Bank (Strategic) | F3: The Scaling Bank (Systematic) | G3: The Adaptive Bank (Leading)
B4: Definitions | C4: "Shadow AI" is prevalent. A credit risk analyst might be experimenting with Python scripts on a local machine, or a marketing team might use off-the-shelf generative AI tools without IT oversight. High regulatory risk due to lack of governance; data privacy vulnerabilities; no strategic alignment with the bank's core goals. | D4: The bank likely establishes an "Innovation Lab" or a "Digital Garage." PoCs are abundant—perhaps a fraud detection pilot or a customer service sentiment analysis tool. These pilots rarely scale to production. They die in the "sandbox" because they cannot integrate with the bank’s legacy core banking systems or fail to meet strict compliance standards. | E4: A Center of Excellence (CoE) is established. The bank creates a standard "AI stack" and data pipeline. Governance moves from "blocking" to "enabling." The focus moves from "What can we do with AI?" to "What should we do to drive ROI?" | F4: AI is no longer a special project; it is part of the standard SDLC. Mortgage approvals, KYC checks, and liquidity forecasting are heavily augmented by AI. The bank creates "reuse" capabilities—a feature store created for credit card fraud is reused for checking account fraud. | G4: The business strategy and AI strategy are indistinguishable. The bank can rapidly ingest new market data and adjust algorithmic trading strategies or risk appetites in near real-time. AI is infused in every customer interaction and back-office process. The bank sets the industry standard for ethical and profitable AI use.
B5: AI Strategy | C5: Fragmented / Shadow AI Ad-hoc use of AI by isolated quants or marketing teams. No formal alignment with bank strategy. | D5: Technical Roadmap Innovation Labs running distinct pilots (e.g., chatbot PoC). Strategy is IT-driven, not business-driven. | E5: Business Aligned AI strategy linked to specific LoB goals (e.g., "Reduce fraud in Cards"). Roadmap includes legacy modernization. | F5: Systematic Management AI is a core component of the bank's strategic plan. Clear roadmap for core banking integration. | G5: Adaptive / AI First Bank's strategy is AI. Real-time adaptation to market shifts using predictive intelligence.
B6: AI Value | C6: Unclear ROI Pilots are treated as "R&D" with no clear P&L targets. High failure rate of projects. | D6: Technical Metrics Success measured by model accuracy (F1 score) rather than dollar value. | E6: Business Case Defined Standardized value framework (Risk vs. Reward). Hard ROI tracked for major initiatives. | F6: Portfolio Optimization Systematic FinOps. "Reuse" of models across departments drives economies of scale. | G6: New Business Models AI drives net-new revenue streams (e.g., Data-as-a-Service, hyper-personalized wealth offers).
B7: AI Organization | C7: Siloed / Isolated Individual analysts working on local machines. No central coordination. | D7: Emerging Teams Formation of a central "Data Science" team or "Digital Garage," often disconnected from risk/compliance. | E7: Hybrid / CoE Center of Excellence (CoE) established. Clear bridge built between IT and Risk/Compliance functions. | F7: Hub & Spoke Data scientists embedded directly into business lines (Mortgage, Commercial), supported by central infra. | G7: Orchestrated Ecosystem Seamless integration of internal teams, external fintechs, and academic partners.
B8: AI People & Culture | C8: Fear & Ignorance Widespread skepticism ("Black Box" fear). Staff views AI as a threat to job security. | D8: Technical Training Training limited to technical staff. Business leaders and risk officers lack AI literacy. | E8: Role-Based Upskilling Targeted training for Compliance and Risk officers to audit AI. "Citizen Developer" pilots begin. | F8: AI Literacy at Scale Bank-wide fluency. Workforce planning actively manages displacement and reskilling. | G8: AI-Augmented Workforce Culture of innovation. Employees across the bank routinely use AI agents to augment tasks.
B9: AI Governance | C9: Non-Existent / High Risk No policies for AI. Use of public tools (ChatGPT) on bank devices without guardrails. | D9: Reactive / Manual governance is a bottleneck. Manual reviews of models delay deployment by months. | E9: MRM Framework Update Model Risk Management (SR 11-7) updated for ML. Policies for fairness/bias established. | F9: Automated Guardrails Governance embedded in code. Automated bias testing and "circuit breakers" in pipelines. | G9: Adaptive Risk Mgmt Real-time monitoring of model drift and adversarial attacks. Governance is an enabler of speed.
B10: AI Engineering | C10: Ad-Hoc / Fragile Models live on desktops or excel. High "Technical Debt." No version control. | D10: Basic Sandbox Cloud environments for testing, but difficult to deploy to legacy core banking systems. | E10: Standardized Platforms Standard "AI Stack" defined. Reusable code libraries for common banking tasks (KYC, Scoring). | F10: Industrialized MLOps CI/CD pipelines for AI. Automated retraining and deployment. Integration with mainframe. | G10: Self-Healing Systems Autonomous operations. Infrastructure scales elastically with real-time transaction volume.
B11: AI Data | C11: Locked / Siloed Data trapped in legacy mainframes. Poor quality and no documentation. | D11: Data Swamp Data collected in lakes but unorganized. "Garbage in, Garbage out" issues. | E11: Structured & Lineage Golden sources identified. Data lineage tracked for regulatory audit trails (BCBS 239). | F11: Data Mesh Real-time data availability. Synthetic data used to train fraud models safely. | G11: Networked Ecosystem External data (Telco, Social) integrated instantly for holistic customer views.

Sheet Assessment & Targets
A1: Category | B1: Sub-Category | C1: Capability | D1: Banking_Context | E1: Source_Ref | F1: Current Maturity (1-5) | G1: Target Maturity (1-5) | H1: Gap | I1: Priority | J1: Comments/Evidence
A2: AI Strategy | B2: Ambition & Vision | C2: Set Vision and Ambition | D2: Is there a board-approved AI vision aligned with specific lines of business (Retail, Wealth, IB)? | E2: Develop and rationalize AI ambition | H2: =IF(OR(ISBLANK(F2), ISBLANK(G2)), "", G2-F2)
B3: Market Trends | C3: Monitor AI Trends | D3: Do we systematically scan for Fintech AI disruptions (e.g., DeFi AI, Quantum Financial) and their impact? | E3: Monitor and interpret AI trends | H3: =IF(OR(ISBLANK(F3), ISBLANK(G3)), "", G3-F3)
B4: Roadmap | C4: Define AI Roadmap | D4: Does a multi-year roadmap exist linking AI investments to core banking platform modernization? | E4: Develop and coordinate AI strategic roadmap | H4: =IF(OR(ISBLANK(F4), ISBLANK(G4)), "", G4-F4)
A5: AI Value | B5: Portfolio Management | C5: Prioritize Use Cases | D5: Are use cases prioritized based on a matrix of P&L value vs. Regulatory Risk/Complexity? | E5: Develop and manage AI use-case portfolio | H5: =IF(OR(ISBLANK(F5), ISBLANK(G5)), "", G5-F5)
B6: Business Cases | C6: Develop Business Cases | D6: Do we have consistent financial models for AI ROI (e.g., cost per contact reduction, fraud savings)? | E6: Develop AI value propositions | H6: =IF(OR(ISBLANK(F6), ISBLANK(G6)), "", G6-F6)
A7: AI Organization | B7: Operating Model | C7: Evolve Internal Operating Model | D7: Is the Hub-and-Spoke model effective? (Centralized Standards vs. Embedded Data Scientists in LoBs). | E7: Evolve internal operating model | H7: =IF(OR(ISBLANK(F7), ISBLANK(G7)), "", G7-F7)
B8: Ecosystem | C8: Manage External Partnerships | D8: Do we effectively manage 3rd-party AI vendor risk (e.g., reliance on black-box vendor models)? | E8: Develop external partnerships | H8: =IF(OR(ISBLANK(F8), ISBLANK(G8)), "", G8-F8)
A9: AI People & Culture | B9: Workforce | C9: Predict Workforce Implications | D9: Have we analyzed the impact of AI/Copilots on junior analyst and support staff roles? | E9: Evolve roles and staffing | H9: =IF(OR(ISBLANK(F9), ISBLANK(G9)), "", G9-F9)
B10: Literacy | C10: Deliver AI Literacy | D10: Is there mandatory training for non-technical staff (Compliance, Legal, Front Office) on Generative AI risks? | E10: Deliver skills, training and literacy | H10: =IF(OR(ISBLANK(F10), ISBLANK(G10)), "", G10-F10)
A11: AI Governance | B11: Policies & Ethics | C11: Develop AI Ethics Frameworks | D11: Do we have explicit fairness/bias testing frameworks (Fair Lending) for customer-facing models? | E11: Create, maintain and evolve AI governance policies | H11: =IF(OR(ISBLANK(F11), ISBLANK(G11)), "", G11-F11)
B12: Risk Management | C12: Develop AI Risk Frameworks | D12: Is AI Model Risk Management (MRM) integrated with SR 11-7 and EU AI Act requirements? | E12: Develop AI risk frameworks | H12: =IF(OR(ISBLANK(F12), ISBLANK(G12)), "", G12-F12)
B13: Oversight | C13: Engineer Oversight Systems | D13: Do we have automated monitoring for Model Drift and Data Drift in production environments? | E13: Engineer oversight systems | H13: =IF(OR(ISBLANK(F13), ISBLANK(G13)), "", G13-F13)
A14: AI Engineering | B14: Architecture | C14: Architect AI Systems | D14: Is the AI architecture decoupled from, yet integrated with, legacy core banking systems? | E14: Design and architect AI applications | H14: =IF(OR(ISBLANK(F14), ISBLANK(G14)), "", G14-F14)
B15: Development | C15: Manage AI Technical Debt | D15: Do we actively track and remediate 'glue code' and hidden dependencies in ML pipelines? | E15: Manage AI technical debt | H15: =IF(OR(ISBLANK(F15), ISBLANK(G15)), "", G15-F15)
B16: Deployment | C16: Operationalize AI Systems (MLOps) | D16: Is the path from 'Jupyter Notebook' to 'Production API' automated and auditable (CI/CD for ML)? | E16: Deploy, operate and scale AI systems | H16: =IF(OR(ISBLANK(F16), ISBLANK(G16)), "", G16-F16)
A17: AI Data | B17: Data Mgmt | C17: Manage and Govern AI Data | D17: Does data governance extend to Feature Stores? Is Lineage traceable for regulatory reporting? | E17: Manage and govern AI Data | H17: =IF(OR(ISBLANK(F17), ISBLANK(G17)), "", G17-F17)
B18: Security | C18: Assure Security and Privacy | D18: Are PII/CSI redaction and data minimization techniques applied specifically for AI training sets? | E18: Assure security and privacy for AI data | H18: =IF(OR(ISBLANK(F18), ISBLANK(G18)), "", G18-F18)
B19: Preparation | C19: Acquire and Prepare Data | D19: Can we rapidly ingest and clean alternative data sources (e.g., transaction logs, external market data)? | E19: Acquire and prepare AI data | H19: =IF(OR(ISBLANK(F19), ISBLANK(G19)), "", G19-F19)

Sheet Gap Visualization Data
A1: Category | B1: Average Current Score | C1: Average Target Score | D1: Average Gap
A2: AI Strategy | B2: =AVERAGEIF('Assessment & Targets'!A:A, A2, 'Assessment & Targets'!F:F) -> #DIV/0! | C2: =AVERAGEIF('Assessment & Targets'!A:A, A2, 'Assessment & Targets'!G:G) -> #DIV/0! | D2: =AVERAGEIF('Assessment & Targets'!A:A, A2, 'Assessment & Targets'!H:H) -> #DIV/0!
A3: AI Value | B3: =AVERAGEIF('Assessment & Targets'!A:A, A3, 'Assessment & Targets'!F:F) -> #DIV/0! | C3: =AVERAGEIF('Assessment & Targets'!A:A, A3, 'Assessment & Targets'!G:G) -> #DIV/0! | D3: =AVERAGEIF('Assessment & Targets'!A:A, A3, 'Assessment & Targets'!H:H) -> #DIV/0!
A4: AI Organization | B4: =AVERAGEIF('Assessment & Targets'!A:A, A4, 'Assessment & Targets'!F:F) -> #DIV/0! | C4: =AVERAGEIF('Assessment & Targets'!A:A, A4, 'Assessment & Targets'!G:G) -> #DIV/0! | D4: =AVERAGEIF('Assessment & Targets'!A:A, A4, 'Assessment & Targets'!H:H) -> #DIV/0!
A5: AI People & Culture | B5: =AVERAGEIF('Assessment & Targets'!A:A, A5, 'Assessment & Targets'!F:F) -> #DIV/0! | C5: =AVERAGEIF('Assessment & Targets'!A:A, A5, 'Assessment & Targets'!G:G) -> #DIV/0! | D5: =AVERAGEIF('Assessment & Targets'!A:A, A5, 'Assessment & Targets'!H:H) -> #DIV/0!
A6: AI Governance | B6: =AVERAGEIF('Assessment & Targets'!A:A, A6, 'Assessment & Targets'!F:F) -> #DIV/0! | C6: =AVERAGEIF('Assessment & Targets'!A:A, A6, 'Assessment & Targets'!G:G) -> #DIV/0! | D6: =AVERAGEIF('Assessment & Targets'!A:A, A6, 'Assessment & Targets'!H:H) -> #DIV/0!
A7: AI Engineering | B7: =AVERAGEIF('Assessment & Targets'!A:A, A7, 'Assessment & Targets'!F:F) -> #DIV/0! | C7: =AVERAGEIF('Assessment & Targets'!A:A, A7, 'Assessment & Targets'!G:G) -> #DIV/0! | D7: =AVERAGEIF('Assessment & Targets'!A:A, A7, 'Assessment & Targets'!H:H) -> #DIV/0!
A8: AI Data | B8: =AVERAGEIF('Assessment & Targets'!A:A, A8, 'Assessment & Targets'!F:F) -> #DIV/0! | C8: =AVERAGEIF('Assessment & Targets'!A:A, A8, 'Assessment & Targets'!G:G) -> #DIV/0! | D8: =AVERAGEIF('Assessment & Targets'!A:A, A8, 'Assessment & Targets'!H:H) -> #DIV/0!
